javaobj.py
obj0.ser
obj1.ser
obj2.ser
obj3.ser
obj4.ser
obj5.ser
obj6.ser
obj7.ser
objArrays.ser
objSuper.ser
setup.py
sunExample.ser
tests.py
java/.classpath
java/.project
java/src/JFrameTest.java
java/src/OneTest.java
javaobj.egg-info/PKG-INFO
javaobj.egg-info/SOURCES.txt
javaobj.egg-info/dependency_links.txt
javaobj.egg-info/top_level.txt