Metadata-Version: 1.0
Name: javaobj
Version: 0.1.0
Summary: Module for serializing and de-serializing Java objects.
Home-page: http://code.google.com/p/python-javaobj
Author: Volodymyr Buell
Author-email: vbuell@gmail.com
License: APL2
Keywords: python java marshalling serialization
Platform: UNKNOWN
Classifier: Development Status :: 3 - Alpha
Classifier: License :: OSI Approved :: Apache Software License
Classifier: Topic :: Software Development :: Libraries :: Python Modules
